Metadata-Version: 2.1
Name: linalgebra-vb
Version: 0.1
Summary: Linear Algebra Calculations
Author: Vasileios Baltas
Author-email: baltasvasileios@gmail.com
